HISTORY.rst
LICENSE.rst
MANIFEST.in
README.rst
requirements.txt
requirements_dev.txt
requirements_test.txt
setup.cfg
setup.py
dynamake/__init__.py
dynamake/__main__.py
dynamake/py.typed
dynamake.egg-info/PKG-INFO
dynamake.egg-info/SOURCES.txt
dynamake.egg-info/dependency_links.txt
dynamake.egg-info/entry_points.txt
dynamake.egg-info/requires.txt
dynamake.egg-info/top_level.txt
tests/__init__.py
tests/test_make.py
tests/test_patterns.py
tests/test_stat.py