Metadata-Version: 2.1
Name: dynamake
Version: 0.6.2
Summary: Dynamic Make in Python
Home-page: https://github.com/orenbenkiki/dynamake.git
Author: Oren Ben-Kiki
Author-email: oren@ben-kiki.org
License: MIT license
Keywords: dynamake,make
Platform: UNKNOWN
Classifier: Development Status :: 2 - Pre-Alpha
Classifier: Intended Audience :: Developers
Classifier: Natural Language :: English
Classifier: Programming Language :: Python :: 3
Classifier: Programming Language :: Python :: 3.7
Classifier: Programming Language :: Python :: 3.8
Classifier: Programming Language :: Python :: 3.9
Requires-Python: >=3.7
Provides-Extra: dev
License-File: LICENSE.rst
